lazier/__init__.py
lazier-0.0.1.dist-info/METADATA
lazier-0.0.1.dist-info/RECORD
lazier-0.0.1.dist-info/WHEEL
lazier-0.0.1.dist-info/top_level.txt
