Metadata-Version: 2.1
Name: lazier
Version: 0.0.1
Summary: Lazier workflow for Jupyter
Home-page: https://github.com/arjunbazinga/lazier
Author: Arjun Srivastava
Author-email: arjunbazinga@gmail.com
License: UNKNOWN
Platform: UNKNOWN
Classifier: Programming Language :: Python :: 3
Classifier: License :: OSI Approved :: MIT License
Classifier: Operating System :: OS Independent
